pdstock/__init__.py
pdstock/stock.py
pdstock-1.2.dist-info/LICENSE.txt
pdstock-1.2.dist-info/METADATA
pdstock-1.2.dist-info/WHEEL
pdstock-1.2.dist-info/top_level.txt
pdstock-1.2.dist-info/RECORD
