Metadata-Version: 2.1
Name: pdstock
Version: 1.2
Summary: This package is for downloading stock market data of companies
Author: Florence Idowu
Author-email: idowuflorence93@gmail.com
Classifier: Programming Language :: Python :: 3
Classifier: License :: OSI Approved :: MIT License
Classifier: Operating System :: OS Independent
License-File: LICENSE.txt
Requires-Dist: pandas
